{
  "results": [
    {
      "id": "1",
      "name": "My Collection 1",
      "numberOfItems": 10,
      "creationDate": "2024-04-04T12:00:00.000Z",
      "lastUpdated": "2024-04-04T12:00:00.000Z"
    },
    {
      "id": "2",
      "name": "My Collection 2",
      "numberOfItems": 20,
      "creationDate": "2024-04-04T12:00:00.000Z",
      "lastUpdated": "2024-04-04T12:00:00.000Z"
    },
    {
      "id": "3",
      "name": "My Collection 3",
      "numberOfItems": 30,
      "creationDate": "2024-04-04T12:00:00.000Z",
      "lastUpdated": "2024-04-04T12:00:00.000Z"
    },
    {
      "id": "4",
      "name": "My Collection 4",
      "numberOfItems": 40,
      "creationDate": "2024-04-04T12:00:00.000Z",
      "lastUpdated": "2024-04-04T12:00:00.000Z"
    },
    {
      "id": "5",
      "name": "My Collection 5",
      "numberOfItems": 50,
      "creationDate": "2024-04-04T12:00:00.000Z",
      "lastUpdated": "2024-04-04T12:00:00.000Z"
    },
    {
      "id": "dfd3a724-58d5-4563-bef2-6387bb87da96",
      "name": "test",
      "numberOfItems": 0,
      "creationDate": "2024-04-07T01:15:11.329Z",
      "lastUpdated": "2024-04-07T01:15:11.329Z"
    },
    {
      "id": "476a39bd-0d9a-4add-8315-9fccd2773c06",
      "name": "test1",
      "numberOfItems": 0,
      "creationDate": "2024-04-07T01:15:36.759Z",
      "lastUpdated": "2024-04-07T01:15:36.759Z"
    },
    {
      "id": "341ee9e4-27f0-45bf-b109-7b63e61a766b",
      "name": "test2",
      "numberOfItems": 0,
      "creationDate": "2024-04-07T01:19:52.882Z",
      "lastUpdated": "2024-04-07T01:19:52.882Z"
    },
    {
      "id": "099f9f5d-c3ad-4b6e-9bd2-a17a9b14f0c3",
      "name": "test4",
      "numberOfItems": 0,
      "creationDate": "2024-04-07T01:20:22.679Z",
      "lastUpdated": "2024-04-07T01:20:22.679Z"
    },
    {
      "id": "f5fb10e5-b0a2-4776-8a10-a6cdddc3e628",
      "name": "test5",
      "numberOfItems": 0,
      "creationDate": "2024-04-07T01:20:40.923Z",
      "lastUpdated": "2024-04-07T01:20:40.923Z"
    }
  ]
}